napari_deepfinder/__init__.py
napari_deepfinder/_cluster_widget.py
napari_deepfinder/_orthoview_widget.py
napari_deepfinder/_reader.py
napari_deepfinder/_segmentation_widget.py
napari_deepfinder/_widget.py
napari_deepfinder/_writer.py
napari_deepfinder/napari.yaml
napari_deepfinder/_tests/__init__.py
napari_deepfinder/_tests/test_reader.py
napari_deepfinder/_tests/test_widget.py
napari_deepfinder/_tests/test_writer.py
napari_deepfinder-0.0.2.dist-info/licenses/LICENSE
napari_deepfinder-0.0.2.dist-info/METADATA
napari_deepfinder-0.0.2.dist-info/WHEEL
napari_deepfinder-0.0.2.dist-info/entry_points.txt
napari_deepfinder-0.0.2.dist-info/top_level.txt
napari_deepfinder-0.0.2.dist-info/RECORD
