Metadata-Version: 2.4
Name: napari-deepfinder
Version: 0.0.2
Summary: A napari plugin for the DeepFinder library which includes display, annotation, target generation, segmentation and clustering functionalities. An orthoslice view has been added for an easier visualisation and annotation process.
Home-page: https://github.com/deep-finder/napari-deepfinder
Author: Constantin Aronssohn
Author-email: cnstt@tutanota.com
License: GPL-3.0-only
Project-URL: Bug Tracker, https://github.com/deep-finder/napari-deepfinder/issues
Project-URL: Documentation, https://deep-finder.github.io/napari-deepfinder/
Project-URL: Source Code, https://github.com/deep-finder/napari-deepfinder
Project-URL: User Support, https://github.com/deep-finder/napari-deepfinder/issues
Classifier: Development Status :: 3 - Alpha
Classifier: Intended Audience :: Education
Classifier: Intended Audience :: Science/Research
Classifier: Framework :: napari
Classifier: Topic :: Scientific/Engineering
Classifier: Topic :: Scientific/Engineering :: Visualization
Classifier: Topic :: Scientific/Engineering :: Information Analysis
Classifier: Topic :: Scientific/Engineering :: Bio-Informatics
Classifier: Topic :: Scientific/Engineering :: Artificial Intelligence
Classifier: Topic :: Scientific/Engineering :: Image Processing
Classifier: Programming Language :: Python
Classifier: Programming Language :: Python :: 3
Classifier: Programming Language :: Python :: 3.9
Classifier: Programming Language :: Python :: 3.10
Classifier: Programming Language :: Python :: 3.11
Classifier: Operating System :: OS Independent
Classifier: License :: OSI Approved :: GNU General Public License v3 (GPLv3)
Requires-Python: >=3.9
License-File: LICENSE
Requires-Dist: cryoet-deepfinder
Requires-Dist: numpy
Requires-Dist: magicgui
Requires-Dist: qtpy
Requires-Dist: napari
Requires-Dist: scikit-image
Requires-Dist: typing
Requires-Dist: pandas
Requires-Dist: lxml[html_clean]
Requires-Dist: pillow
Requires-Dist: h5py
Requires-Dist: mrcfile
Requires-Dist: scipy
Provides-Extra: testing
Requires-Dist: tox; extra == "testing"
Requires-Dist: pytest; extra == "testing"
Requires-Dist: pytest-cov; extra == "testing"
Requires-Dist: pytest-qt; extra == "testing"
Dynamic: license-file
